[
  {
    "declaracion": {
      "declaracionCompleta": false,
      "interes": {
        "apoyos": {
          "apoyo": [],
          "ninguno": true
        },
        "beneficiosPrivados": {
          "beneficio": [],
          "ninguno": true
        },
        "clientesPrincipales": {
          "cliente": [],
          "ninguno": true
        },
        "fideicomisos": {
          "fideicomiso": [],
          "ninguno": true
        },
        "participacion": {
          "ninguno": true,
          "participacion": []
        },
        "participacionTomaDecisiones": {
          "ninguno": true,
          "participacion": []
        },
        "representacion": {
          "ninguno": true,
          "representacion": []
        }
      },
      "situacionPatrimonial": {
        "actividadAnualAnterior": {
          "servidorPublicoAnioAnterior": false
        },
        "adeudos": {
          "adeudo": [],
          "ninguno": true
        },
        "bienesInmuebles": {
          "bienInmueble": [],
          "ninguno": true
        },
        "bienesMuebles": {
          "bienMueble": [],
          "ninguno": true
        },
        "datosCurricularesDeclarante": {
          "escolaridad": [
            {
              "carreraAreaConocimiento": "ADMINISTRACIÓN DE EMPRESAS",
              "documentoObtenido": "CONSTANCIA",
              "estatus": "FINALIZADO",
              "fechaObtencion": "2021-04-24",
              "institucionEducativa": {
                "nombre": "UNIVERSIDAD CEUMA",
                "ubicacion": "MX"
              },
              "nivel": {
                "clave": "LIC",
                "valor": "LICENCIATURA"
              },
              "tipoOpeacion": "AGREGAR"
            }
          ]
        },
        "datosEmpleoCargoComision": {
          "ambitoPublico": "EJECUTIVO",
          "areaAdscripcion": "DIRECCIÓN GENERAL",
          "contratadoPorHonorarios": false,
          "domicilioMexico": {
            "calle": "ALLENDE",
            "codigoPostal": "61330",
            "coloniaLocalidad": "CENTRO",
            "entidadFederativa": {
              "clave": "16",
              "valor": "MICHOACÁN DE OCAMPO"
            },
            "municipioAlcaldia": {
              "clave": "101",
              "valor": "TZITZIO"
            },
            "numeroExterior": "S/N",
            "numeroInterior": ""
          },
          "empleoCargoComision": "TITUTLAR",
          "fechaTomaPosesion": "2022-01-01",
          "funcionPrincipal": "ADMINISTRACIÓN TOTAL DEL IMPLATM",
          "nivelEmpleoCargoComision": "PRIMERO",
          "nivelOrdenGobierno": "MUNICIPAL_ALCALDIA",
          "nombreEntePublico": "IMPLATM",
          "telefonoOficina": {
            "extension": "0",
            "telefono": "4593530069"
          },
          "tipoOperacion": "AGREGAR"
        },
        "datosGenerales": {
          "nombre": "MARIA DE LOS ANGELES",
          "primerApellido": "GUTIERREZ",
          "segundoApellido": "VELAZQUEZ"
        },
        "experienciaLaboral": {
          "experiencia": [
            {
              "ambitoSector": {
                "clave": "PRV",
                "valor": "PRIVADO"
              },
              "area": "GERENCIA",
              "fechaEgreso": "2020-04-04",
              "fechaIngreso": "2018-06-01",
              "nombreEmpresaSociedadAsociacion": "FRAYSA SA DE CV",
              "puesto": "AUXILIAR ADMINISTRATIVO",
              "rfc": "FRA1805188X8",
              "sector": {
                "clave": "SERVINM",
                "valor": "SERVICIOS INMOBILIARIOS"
              },
              "tipoOperacion": "AGREGAR",
              "ubicacion": "MX"
            },
            {
              "ambitoSector": {
                "clave": "PRV",
                "valor": "PRIVADO"
              },
              "area": "ATENCIÓN AL CLIENTE",
              "fechaEgreso": "2018-05-18",
              "fechaIngreso": "2011-12-11",
              "nombreEmpresaSociedadAsociacion": "FARMACIA GUADALAJARA SA DE CV",
              "puesto": "SUPLENTE",
              "rfc": "FGU830930PD3",
              "sector": {
                "clave": "SERVS",
                "valor": "SERVICIOS DE SALUD"
              },
              "tipoOperacion": "AGREGAR",
              "ubicacion": "MX"
            }
          ],
          "ninguno": false
        },
        "ingresos": {
          "actividadFinanciera": {
            "actividades": [
              {
                "remuneracion": {
                  "moneda": "MXN",
                  "valor": 0
                },
                "tipoInstrumento": {
                  "clave": "CAP",
                  "valor": "CAPITAL"
                }
              },
              {
                "remuneracion": {
                  "moneda": "MXN",
                  "valor": 0
                },
                "tipoInstrumento": {
                  "clave": "FIN",
                  "valor": "FONDOS DE INVERSIÓN"
                }
              },
              {
                "remuneracion": {
                  "moneda": "MXN",
                  "valor": 0
                },
                "tipoInstrumento": {
                  "clave": "OPR",
                  "valor": "ORGANIZACIONES PRIVADAS"
                }
              },
              {
                "remuneracion": {
                  "moneda": "MXN",
                  "valor": 0
                },
                "tipoInstrumento": {
                  "clave": "SSI",
                  "valor": "SEGURO DE SEPARACIÓN INDIVIDUALIZADO"
                }
              },
              {
                "remuneracion": {
                  "moneda": "MXN",
                  "valor": 0
                },
                "tipoInstrumento": {
                  "clave": "VBU",
                  "valor": "VALORES BURSÁTILES"
                }
              },
              {
                "remuneracion": {
                  "moneda": "MXN",
                  "valor": 0
                },
                "tipoInstrumento": {
                  "clave": "BON",
                  "valor": "BONOS"
                }
              },
              {
                "remuneracion": {
                  "moneda": "MXN",
                  "valor": 0
                },
                "tipoInstrumento": {
                  "clave": "OTRO",
                  "valor": "OTRO (ESPECIFIQUE)"
                }
              }
            ],
            "remuneracionTotal": {
              "moneda": "MXN",
              "valor": 0
            }
          },
          "actividadIndustrialComercialEmpresarial": {
            "actividades": [],
            "remuneracionTotal": {
              "moneda": "MXN",
              "valor": 0
            }
          },
          "ingresoMensualNetoDeclarante": {
            "moneda": "MXN",
            "valor": 8000
          },
          "otrosIngresos": {
            "ingresos": [],
            "remuneracionTotal": {
              "moneda": "MXN",
              "valor": 0
            }
          },
          "otrosIngresosMensualTotal": {
            "moneda": "MXN",
            "valor": 0
          },
          "remuneracionMensualCargoPublico": {
            "moneda": "MXN",
            "valor": 8000
          },
          "serviciosProfesionales": {
            "remuneracionTotal": {
              "moneda": "MXN",
              "valor": 0
            },
            "servicios": []
          },
          "totalIngresosMensualesNetos": {
            "moneda": "MXN",
            "valor": 8000
          }
        },
        "inversiones": {
          "inversion": [],
          "ninguno": true
        },
        "prestamoOComodato": {
          "ninguno": true,
          "prestamo": []
        },
        "vehiculos": {
          "ninguno": true,
          "vehiculo": []
        }
      }
    },
    "id": "gn4kr7q7v4",
    "metadata": {
      "actualizacion": "2022-05-20T10:57:16Z",
      "actualizacionConflictoInteres": false,
      "declaracionCompleta": false,
      "institucion": "AYUNTAMIENTO DE TZITZIO",
      "tipo": "INICIAL"
    }
  }
]
