[
  {
    "declaracion": {
      "declaracionCompleta": false,
      "interes": {
        "apoyos": {
          "apoyo": [],
          "ninguno": true
        },
        "beneficiosPrivados": {
          "beneficio": [],
          "ninguno": true
        },
        "clientesPrincipales": {
          "cliente": [],
          "ninguno": true
        },
        "fideicomisos": {
          "fideicomisos": [],
          "ninguno": true
        },
        "participacion": {
          "ninguno": true,
          "participacion": []
        },
        "participacionTomaDecisiones": {
          "ninguno": true,
          "participacion": []
        },
        "representacion": {
          "ninguno": true,
          "representacion": []
        }
      },
      "situacionPatrimonial": {
        "actividadAnualAnterior": {
          "actividadFinanciera": {
            "actividades": [],
            "remuneracionTotal": {
              "moneda": "",
              "valor": 0
            }
          },
          "actividadIndustrialComercialEmpresarial": {
            "actividades": [],
            "remuneracionTotal": {
              "moneda": "",
              "valor": 0
            }
          },
          "enajenacionBienes": {
            "bienes": [],
            "remuneracionTotal": {
              "moneda": "",
              "valor": 0
            }
          },
          "fechaConclusion": "2020-01-01",
          "fechaIngreso": "2020-01-01",
          "ingresoNetoAnualDeclarante": {
            "moneda": "",
            "valor": 0
          },
          "otrosIngresos": {
            "ingresos": [],
            "remuneracionTotal": {
              "moneda": "",
              "valor": 0
            }
          },
          "otrosIngresosTotal": {
            "moneda": "",
            "valor": 0
          },
          "remuneracionNetaCargoPublico": {
            "moneda": "",
            "valor": 0
          },
          "serviciosProfesionales": {
            "remuneracionTotal": {
              "moneda": "",
              "valor": 0
            },
            "servicios": []
          },
          "servidorPublicoAnioAnterior": true,
          "totalIngresosNetosAnuales": {
            "moneda": "",
            "valor": 0
          }
        },
        "adeudos": {
          "adeudo": [],
          "ninguno": true
        },
        "bienesInmuebles": {
          "bienInmueble": [],
          "ninguno": true
        },
        "bienesMuebles": {
          "bienMueble": [],
          "ninguno": true
        },
        "datosCurricularesDeclarante": {
          "escolaridad": [
            {
              "carreraAreaConocimiento": "LICENCIATURA EN DERECHO Y CIENCIAS SOCIALES",
              "documentoObtenido": "TITULO",
              "estatus": "FINALIZADO",
              "fechaObtencion": "2018-08-08",
              "institucionEducativa": {
                "nombre": "UNIVERSIDAD MICHOACANA DE SAN NICOLAS DE HIDALGO",
                "ubicacion": "MX"
              },
              "nivel": {
                "clave": "LIC",
                "valor": "LICENCIATURA"
              },
              "tipoOperacion": "AGREGAR"
            }
          ]
        },
        "datosEmpleoCargoComision": {
          "ambitoPublico": "EJECUTIVO",
          "areaAdscripcion": "SECRETARÍA PARTICULAR",
          "contratadoPorHonorarios": false,
          "domicilioExtranjero": {
            "calle": "AV. CHIAPAS",
            "ciudadLocalidad": "No especificado",
            "codigoPostal": "60050",
            "estadoProvincia": "No especificado",
            "numeroExterior": "93",
            "numeroInterior": "201",
            "pais": "MX"
          },
          "domicilioMexico": {
            "calle": "AV. CHIAPAS",
            "codigoPostal": "60050",
            "coloniaLocalidad": "RAMON FARIAS",
            "entidadFederativa": {
              "clave": "16",
              "valor": "Michoacán de Ocampo"
            },
            "municipioAlcaldia": {
              "clave": "102",
              "valor": "Uruapan"
            },
            "numeroExterior": "93",
            "numeroInterior": "201"
          },
          "empleoCargoComision": "AUXILIAR ADMINISTRATIVO ESPECIALIZADO",
          "fechaTomaPosesion": "2021-08-01",
          "funcionPrincipal": "Atención directa al público",
          "nivelEmpleoCargoComision": "1",
          "nivelOrdenGobierno": "MUNICIPAL_ALCALDIA",
          "nombreEntePublico": "Municipio de Uruapan Michoacán",
          "telefonoOficina": {
            "extension": "",
            "telefono": "4525242398"
          },
          "tipoOperacion": "AGREGAR"
        },
        "datosGenerales": {
          "nombre": "VERONICA",
          "primerApellido": "TORRES",
          "segundoApellido": "MARTINEZ"
        },
        "experienciaLaboral": {
          "experiencia": [],
          "ninguno": true
        },
        "ingresos": {
          "actividadFinanciera": {
            "actividades": [],
            "remuneracionTotal": {
              "moneda": "",
              "valor": 0
            }
          },
          "actividadIndustrialComercialEmpresarial": {
            "actividades": [],
            "remuneracionTotal": {
              "moneda": "",
              "valor": 0
            }
          },
          "ingresoMensualNetoDeclarante": {
            "moneda": "MXN",
            "valor": 11716
          },
          "otrosIngresos": {
            "ingresos": [],
            "remuneracionTotal": {
              "moneda": "",
              "valor": 0
            }
          },
          "otrosIngresosMensualesTotal": {
            "moneda": "",
            "valor": 0
          },
          "remuneracionMensualCargoPublico": {
            "moneda": "MXN",
            "valor": 11716
          },
          "serviciosProfesionales": {
            "remuneracionTotal": {
              "moneda": "",
              "valor": 0
            },
            "servicios": []
          },
          "servidorPublicoAnioAnterior": false,
          "totalIngresosMensualesNetos": {
            "moneda": "MXN",
            "valor": 11716
          }
        },
        "inversiones": {
          "inversion": [],
          "ninguno": true
        },
        "prestamoOComodato": {
          "ninguno": true,
          "prestamo": []
        },
        "vehiculos": {
          "ninguno": true,
          "vehiculo": []
        }
      }
    },
    "id": "c5xa8f4ts8",
    "metadata": {
      "actualizacion": "2021-09-11T00:00:00Z",
      "actualizacionConflictoInteres": false,
      "declaracionCompleta": false,
      "institucion": "Municipio de Uruapan Michoacán",
      "tipo": "INICIAL"
    }
  }
]
