[
  {
    "declaracion": {
      "declaracionCompleta": false,
      "interes": {
        "apoyos": {
          "apoyo": [],
          "ninguno": true
        },
        "beneficiosPrivados": {
          "beneficio": [],
          "ninguno": true
        },
        "clientesPrincipales": {
          "cliente": [],
          "ninguno": true
        },
        "fideicomisos": {
          "fideicomisos": [],
          "ninguno": true
        },
        "participacion": {
          "ninguno": true,
          "participacion": []
        },
        "participacionTomaDecisiones": {
          "ninguno": true,
          "participacion": []
        },
        "representacion": {
          "ninguno": true,
          "representacion": []
        }
      },
      "situacionPatrimonial": {
        "actividadAnualAnterior": {
          "actividadFinanciera": {
            "actividades": [],
            "remuneracionTotal": {
              "moneda": "",
              "valor": 0
            }
          },
          "actividadIndustrialComercialEmpresarial": {
            "actividades": [],
            "remuneracionTotal": {
              "moneda": "",
              "valor": 0
            }
          },
          "enajenacionBienes": {
            "bienes": [],
            "remuneracionTotal": {
              "moneda": "",
              "valor": 0
            }
          },
          "fechaConclusion": "2020-01-01",
          "fechaIngreso": "2020-01-01",
          "ingresoNetoAnualDeclarante": {
            "moneda": "",
            "valor": 0
          },
          "otrosIngresos": {
            "ingresos": [],
            "remuneracionTotal": {
              "moneda": "",
              "valor": 0
            }
          },
          "otrosIngresosTotal": {
            "moneda": "",
            "valor": 0
          },
          "remuneracionNetaCargoPublico": {
            "moneda": "",
            "valor": 0
          },
          "serviciosProfesionales": {
            "remuneracionTotal": {
              "moneda": "",
              "valor": 0
            },
            "servicios": []
          },
          "servidorPublicoAnioAnterior": true,
          "totalIngresosNetosAnuales": {
            "moneda": "",
            "valor": 0
          }
        },
        "adeudos": {
          "adeudo": [],
          "ninguno": true
        },
        "bienesInmuebles": {
          "bienInmueble": [],
          "ninguno": true
        },
        "bienesMuebles": {
          "bienMueble": [],
          "ninguno": true
        },
        "datosCurricularesDeclarante": {
          "escolaridad": [
            {
              "carreraAreaConocimiento": "Secundaria",
              "documentoObtenido": "CERTIFICADO",
              "estatus": "FINALIZADO",
              "fechaObtencion": "1987-06-04",
              "institucionEducativa": {
                "nombre": "Benito Juárez",
                "ubicacion": "MX"
              },
              "nivel": {
                "clave": "SEC",
                "valor": "SECUNDARIA"
              },
              "tipoOperacion": "AGREGAR"
            }
          ]
        },
        "datosEmpleoCargoComision": {
          "ambitoPublico": "EJECUTIVO",
          "areaAdscripcion": "SECRETARÍA DE SEGURIDAD PÚBLICA",
          "contratadoPorHonorarios": false,
          "domicilioExtranjero": {
            "calle": "Naranjos esq. Con eucaliptos",
            "ciudadLocalidad": "No especificado",
            "codigoPostal": "60190",
            "estadoProvincia": "No especificado",
            "numeroExterior": "S/N",
            "numeroInterior": "S/n",
            "pais": "MX"
          },
          "domicilioMexico": {
            "calle": "Naranjos esq. Con eucaliptos",
            "codigoPostal": "60190",
            "coloniaLocalidad": "Fraccionamiento miraflores",
            "entidadFederativa": {
              "clave": "16",
              "valor": "Michoacán de Ocampo"
            },
            "municipioAlcaldia": {
              "clave": "102",
              "valor": "Uruapan"
            },
            "numeroExterior": "S/N",
            "numeroInterior": "S/n"
          },
          "empleoCargoComision": "COCINERO",
          "fechaTomaPosesion": "2021-06-07",
          "funcionPrincipal": "Otro (Especifique)",
          "nivelEmpleoCargoComision": "3",
          "nivelOrdenGobierno": "MUNICIPAL_ALCALDIA",
          "nombreEntePublico": "Municipio de Uruapan Michoacán",
          "telefonoOficina": {
            "extension": "",
            "telefono": "4525240620"
          },
          "tipoOperacion": "AGREGAR"
        },
        "datosGenerales": {
          "nombre": "OLGA LETICIA",
          "primerApellido": "MATADAMAS",
          "segundoApellido": "PAULIN"
        },
        "experienciaLaboral": {
          "experiencia": [],
          "ninguno": true
        },
        "ingresos": {
          "actividadFinanciera": {
            "actividades": [],
            "remuneracionTotal": {
              "moneda": "",
              "valor": 0
            }
          },
          "actividadIndustrialComercialEmpresarial": {
            "actividades": [],
            "remuneracionTotal": {
              "moneda": "",
              "valor": 0
            }
          },
          "ingresoMensualNetoDeclarante": {
            "moneda": "MXN",
            "valor": 37070
          },
          "otrosIngresos": {
            "ingresos": [],
            "remuneracionTotal": {
              "moneda": "",
              "valor": 0
            }
          },
          "otrosIngresosMensualesTotal": {
            "moneda": "",
            "valor": 0
          },
          "remuneracionMensualCargoPublico": {
            "moneda": "MXN",
            "valor": 37070
          },
          "serviciosProfesionales": {
            "remuneracionTotal": {
              "moneda": "",
              "valor": 0
            },
            "servicios": []
          },
          "servidorPublicoAnioAnterior": false,
          "totalIngresosMensualesNetos": {
            "moneda": "MXN",
            "valor": 37070
          }
        },
        "inversiones": {
          "inversion": [],
          "ninguno": true
        },
        "prestamoOComodato": {
          "ninguno": true,
          "prestamo": []
        },
        "vehiculos": {
          "ninguno": true,
          "vehiculo": []
        }
      }
    },
    "id": "xgenr7ghfp",
    "metadata": {
      "actualizacion": "2022-07-13T00:00:00Z",
      "actualizacionConflictoInteres": false,
      "declaracionCompleta": false,
      "institucion": "Municipio de Uruapan Michoacán",
      "tipo": "INICIAL"
    }
  }
]
