[
  {
    "declaracion": {
      "declaracionCompleta": true,
      "interes": {
        "apoyos": {
          "aclaracionesObservaciones": "",
          "apoyo": [],
          "ninguno": true
        },
        "beneficiosPrivados": {
          "aclaracionesObservaciones": "",
          "beneficio": [],
          "ninguno": true
        },
        "clientesPrincipales": {
          "aclaracionesObservaciones": "",
          "cliente": [],
          "ninguno": true
        },
        "fideicomisos": {
          "aclaracionesObservaciones": "",
          "fideicomiso": [],
          "ninguno": true
        },
        "participacion": {
          "aclaracionesObservaciones": "",
          "ninguno": true,
          "participacion": []
        },
        "participacionTomaDecisiones": {
          "aclaracionesObservaciones": "",
          "ninguno": true,
          "participacion": []
        },
        "representaciones": {
          "aclaracionesObservaciones": "",
          "ninguno": true,
          "representacion": []
        }
      },
      "situacionPatrimonial": {
        "actividadAnualAnterior": {
          "aclaracionesObservaciones": "",
          "servidorPublicoAnioAnterior": true
        },
        "adeudosPasivos": {
          "aclaracionesObservaciones": "",
          "adeudo": [],
          "ninguno": true
        },
        "bienesInmuebles": {
          "aclaracionesObservaciones": "",
          "bienInmueble": [],
          "ninguno": true
        },
        "bienesMuebles": {
          "aclaracionesObservaciones": "",
          "bienMueble": [],
          "ninguno": true
        },
        "datosCurricularesDeclarante": {
          "aclaracionesObservaciones": "",
          "escolaridad": [
            {
              "carreraAreaConocimiento": "EDUCACIÓN MEDIA SUPERIOR",
              "documentoObtenido": "CERTIFICADO",
              "estatus": "FINALIZADO",
              "fechaObtencion": "2022-03-02",
              "institucionEducativa": {
                "nombre": "instituto osmar",
                "ubicacion": "MX"
              },
              "nivel": {
                "clave": "BCH",
                "valor": "BACHILLERATO"
              },
              "tipoOperacion": "AGREGAR"
            }
          ],
          "ninguno": false
        },
        "datosDependientesEconomicos": {
          "aclaracionesObservaciones": "",
          "dependienteEconomico": [
            {
              "actividadLaboral": {
                "clave": "NIN",
                "valor": "NINGUNO"
              },
              "curp": "",
              "domicilioMexico": {
                "calle": "rio cupatitzio",
                "codigoPostal": "58149",
                "coloniaLocalidad": "Ampliación Eduardo Ruíz",
                "entidadFederativa": {
                  "clave": "16",
                  "valor": "Michoacán de Ocampo"
                },
                "municipioAlcaldia": {
                  "clave": "053",
                  "valor": "Morelia"
                },
                "numeroExterior": "1025",
                "numeroInterior": ""
              },
              "extranjero": false,
              "fechaNacimiento": "2012-06-10",
              "habitaDomicilioDeclarante": false,
              "lugarDondeReside": "MEXICO",
              "nombre": "santiago",
              "parentescoRelacion": {
                "clave": "HIJ",
                "valor": "HIJO(A)"
              },
              "primerApellido": "villanueva",
              "rfc": "",
              "segundoApellido": "barron",
              "tipoOperacion": "AGREGAR"
            },
            {
              "actividadLaboral": {
                "clave": "NIN",
                "valor": "NINGUNO"
              },
              "curp": "",
              "extranjero": false,
              "fechaNacimiento": "2017-09-04",
              "habitaDomicilioDeclarante": false,
              "lugarDondeReside": "SE_DESCONOCE",
              "nombre": "mario",
              "parentescoRelacion": {
                "clave": "HIJ",
                "valor": "HIJO(A)"
              },
              "primerApellido": "villanueva",
              "rfc": "",
              "segundoApellido": "barron",
              "tipoOperacion": "AGREGAR"
            }
          ],
          "ninguno": false
        },
        "datosEmpleoCargoComision": {
          "aclaracionesObservaciones": "",
          "ambitoPublico": "EJECUTIVO",
          "areaAdscripcion": "seguridad pública",
          "clasificacion": "Personal de confianza",
          "contratadoPorHonorarios": false,
          "domicilioMexico": {
            "calle": "portal independencia",
            "codigoPostal": "58450",
            "coloniaLocalidad": "Lagunillas",
            "entidadFederativa": {
              "clave": "16",
              "valor": "Michoacán de Ocampo"
            },
            "municipioAlcaldia": {
              "clave": "048",
              "valor": "Lagunillas"
            },
            "numeroExterior": "25",
            "numeroInterior": ""
          },
          "empleoCargoComision": "POLICIA MUNICIPAL",
          "fechaTomaPosesion": "2022-09-04",
          "funcionPrincipal": "operativa",
          "nivelEmpleoCargoComision": "RAZO",
          "nivelOrdenGobierno": "MUNICIPAL_ALCALDIA",
          "nombreEntePublico": "LAGUNILLAS",
          "telefonoOficina": {
            "extension": "",
            "lada": "52",
            "telefono": "4341175880"
          },
          "tipoOperacion": "AGREGAR"
        },
        "datosGenerales": {
          "nombre": "MARIO COPERNICO",
          "primerApellido": "VILLANUEVA",
          "segundoApellido": "GARCIA"
        },
        "datosPareja": {
          "aclaracionesObservaciones": "",
          "ninguno": true
        },
        "domicilioDeclarante": {
          "aclaracionesObservaciones": "",
          "domicilioMexico": {
            "calle": "rio cupatitzio",
            "codigoPostal": "58149",
            "coloniaLocalidad": "Ampliación Eduardo Ruíz",
            "entidadFederativa": {
              "clave": "16",
              "valor": "Michoacán de Ocampo"
            },
            "municipioAlcaldia": {
              "clave": "053",
              "valor": "Morelia"
            },
            "numeroExterior": "1025",
            "numeroInterior": ""
          }
        },
        "experienciaLaboral": {
          "aclaracionesObservaciones": "experienciaLaboral",
          "experiencia": [
            {
              "ambitoPublico": "LEGISLATIVO",
              "ambitoSector": {
                "clave": "PUB",
                "valor": "Público"
              },
              "areaAdscripcion": "seguridad publica",
              "empleoCargoComision": "policia",
              "fechaEgreso": "2021-04-23",
              "fechaIngreso": "2016-01-01",
              "funcionPrincipal": "operativa",
              "nivelOrdenGobierno": "ESTATAL",
              "nombreEntePublico": "secretaria de seguridad publica del estado",
              "tipoOperacion": "AGREGAR",
              "ubicacion": "MX"
            }
          ],
          "ninguno": false
        },
        "ingresos": {
          "aclaracionesObservaciones": "",
          "actividadFinanciera": {
            "actividades": [],
            "remuneracionTotal": {
              "moneda": "MXN",
              "valor": 0
            }
          },
          "actividadIndustrialComercialEmpresarial": {
            "actividades": [],
            "remuneracionTotal": {
              "moneda": "MXN",
              "valor": 0
            }
          },
          "ingresoMensualNetoDeclarante": {
            "moneda": "MXN",
            "valor": 23400
          },
          "ingresoMensualNetoParejaDependiente": {
            "moneda": "MXN",
            "valor": 0
          },
          "otrosIngresos": {
            "ingresos": [],
            "remuneracionTotal": {
              "moneda": "MXN",
              "valor": 0
            }
          },
          "otrosIngresosMensualesTotal": {
            "moneda": "MXN",
            "valor": 0
          },
          "remuneracionMensualCargoPublico": {
            "moneda": "MXN",
            "valor": 23400
          },
          "serviciosProfesionales": {
            "remuneracionTotal": {
              "moneda": "MXN",
              "valor": 0
            },
            "servicios": []
          },
          "totalIngresosMensualesNetos": {
            "moneda": "MXN",
            "valor": 23400
          }
        },
        "inversionesCuentasValores": {
          "aclaracionesObservaciones": "",
          "inversion": [],
          "ninguno": true
        },
        "prestamoComodato": {
          "aclaracionesObservaciones": "",
          "ninguno": true,
          "prestamo": []
        },
        "vehiculos": {
          "aclaracionesObservaciones": "",
          "ninguno": true,
          "vehiculo": []
        }
      }
    },
    "id": "tqmy7sq7ts",
    "metadata": {
      "actualizacion": "2022-12-07T17:03:32Z",
      "actualizacionConflictoInteres": false,
      "declaracionCompleta": true,
      "institucion": "LAGUNILLAS",
      "tipo": "INICIAL"
    }
  }
]
